{
  "id": "573/2007",
  "type": "statute",
  "title": "Laki ulkomaille maksettavasta rintamalisästä annetun lain 2 ja 10 § :n muuttamisesta",
  "title_en": "Lag om ändring av 2 och 10 § i lagen om betalning av fronttillägg utomlands",
  "status": "in_force",
  "issued_date": "2007-05-11",
  "in_force_date": "2007-05-11",
  "url": "https://opendata.finlex.fi/finlex/avoindata/v1/akn/fi/act/statute/2007/573/fin@",
  "description": "Ingested from Finlex open data (amending-statute)",
  "provisions": [
    {
      "provision_ref": "2",
      "section": "2",
      "content": "Rintamalisä myönnetään ulkomailla asuvalle henkilölle, joka ei saa kansaneläkelain (568/2007) mukaista kansaneläkettä.",
      "metadata": {
        "source": "finlex",
        "source_eid": "flat:2",
        "normalized_fi": "Rintamalisä myönnetään ulkomailla asuvalle henkilölle, joka ei saa kansaneläkelain (568/2007) mukaista kansaneläkettä.",
        "folded_fi": "rintamalisa myonnetaan ulkomailla asuvalle henkilolle, joka ei saa kansanelakelain (568/2007) mukaista kansanelaketta.",
        "content_sv": "Fronttillägg beviljas en person som är bosatt utomlands och som inte får folkpension enligt folkpensionslagen (568/2007).",
        "normalized_sv": "Fronttillägg beviljas en person som är bosatt utomlands och som inte får folkpension enligt folkpensionslagen (568/2007).",
        "folded_sv": "fronttillagg beviljas en person som ar bosatt utomlands och som inte far folkpension enligt folkpensionslagen (568/2007)."
      }
    },
    {
      "provision_ref": "10",
      "section": "10",
      "content": "Jollei tässä laissa toisin säädetä, noudatetaan soveltuvin osin, mitä kansaneläkelain 54 §:n 1 ja 2 momentissa, 63, 75―84, 86, 91, 96, 106 ja 107 §:ssä, 110 §:n 2 momentissa ja 111 §:ssä sekä kansaneläkeindeksistä annetussa laissa (456/2001) säädetään.",
      "metadata": {
        "source": "finlex",
        "source_eid": "flat:10",
        "normalized_fi": "Jollei tässä laissa toisin säädetä, noudatetaan soveltuvin osin, mitä kansaneläkelain 54 § :n 1 ja 2 momentissa, 63, 75―84, 86, 91, 96, 106 ja 107 § :ssä, 110 § :n 2 momentissa ja 111 § :ssä sekä kansaneläkeindeksistä annetussa laissa (456/2001) säädetään.",
        "folded_fi": "jollei tassa laissa toisin saadeta, noudatetaan soveltuvin osin, mita kansanelakelain 54 §:n 1 ja 2 momentissa, 63, 75―84, 86, 91, 96, 106 ja 107 §:ssa, 110 §:n 2 momentissa ja 111 §:ssa seka kansanelakeindeksista annetussa laissa (456/2001) saadetaan.",
        "content_sv": "Om inte något annat bestäms i denna lag, iakttas i tillämpliga delar 54 § 1 och 2 mom., 63, 75―84, 86, 91, 96, 106 och 107 §, 110 § 2 mom. och 111 § i folkpensionslagen samt lagen om folkpensionsindex (456/2001).",
        "normalized_sv": "Om inte något annat bestäms i denna lag, iakttas i tillämpliga delar 54 § 1 och 2 mom., 63, 75―84, 86, 91, 96, 106 och 107 § , 110 § 2 mom. och 111 § i folkpensionslagen samt lagen om folkpensionsindex (456/2001).",
        "folded_sv": "om inte nagot annat bestams i denna lag, iakttas i tillampliga delar 54 § 1 och 2 mom., 63, 75―84, 86, 91, 96, 106 och 107 §, 110 § 2 mom. och 111 § i folkpensionslagen samt lagen om folkpensionsindex (456/2001)."
      }
    }
  ],
  "provision_versions": [
    {
      "provision_ref": "2",
      "section": "2",
      "content": "Rintamalisä myönnetään ulkomailla asuvalle henkilölle, joka ei saa kansaneläkelain (568/2007) mukaista kansaneläkettä.",
      "metadata": {
        "source": "finlex",
        "source_eid": "flat:2",
        "normalized_fi": "Rintamalisä myönnetään ulkomailla asuvalle henkilölle, joka ei saa kansaneläkelain (568/2007) mukaista kansaneläkettä.",
        "folded_fi": "rintamalisa myonnetaan ulkomailla asuvalle henkilolle, joka ei saa kansanelakelain (568/2007) mukaista kansanelaketta.",
        "content_sv": "Fronttillägg beviljas en person som är bosatt utomlands och som inte får folkpension enligt folkpensionslagen (568/2007).",
        "normalized_sv": "Fronttillägg beviljas en person som är bosatt utomlands och som inte får folkpension enligt folkpensionslagen (568/2007).",
        "folded_sv": "fronttillagg beviljas en person som ar bosatt utomlands och som inte far folkpension enligt folkpensionslagen (568/2007)."
      },
      "valid_from": "2007-05-11",
      "valid_to": null
    },
    {
      "provision_ref": "10",
      "section": "10",
      "content": "Jollei tässä laissa toisin säädetä, noudatetaan soveltuvin osin, mitä kansaneläkelain 54 §:n 1 ja 2 momentissa, 63, 75―84, 86, 91, 96, 106 ja 107 §:ssä, 110 §:n 2 momentissa ja 111 §:ssä sekä kansaneläkeindeksistä annetussa laissa (456/2001) säädetään.",
      "metadata": {
        "source": "finlex",
        "source_eid": "flat:10",
        "normalized_fi": "Jollei tässä laissa toisin säädetä, noudatetaan soveltuvin osin, mitä kansaneläkelain 54 § :n 1 ja 2 momentissa, 63, 75―84, 86, 91, 96, 106 ja 107 § :ssä, 110 § :n 2 momentissa ja 111 § :ssä sekä kansaneläkeindeksistä annetussa laissa (456/2001) säädetään.",
        "folded_fi": "jollei tassa laissa toisin saadeta, noudatetaan soveltuvin osin, mita kansanelakelain 54 §:n 1 ja 2 momentissa, 63, 75―84, 86, 91, 96, 106 ja 107 §:ssa, 110 §:n 2 momentissa ja 111 §:ssa seka kansanelakeindeksista annetussa laissa (456/2001) saadetaan.",
        "content_sv": "Om inte något annat bestäms i denna lag, iakttas i tillämpliga delar 54 § 1 och 2 mom., 63, 75―84, 86, 91, 96, 106 och 107 §, 110 § 2 mom. och 111 § i folkpensionslagen samt lagen om folkpensionsindex (456/2001).",
        "normalized_sv": "Om inte något annat bestäms i denna lag, iakttas i tillämpliga delar 54 § 1 och 2 mom., 63, 75―84, 86, 91, 96, 106 och 107 § , 110 § 2 mom. och 111 § i folkpensionslagen samt lagen om folkpensionsindex (456/2001).",
        "folded_sv": "om inte nagot annat bestams i denna lag, iakttas i tillampliga delar 54 § 1 och 2 mom., 63, 75―84, 86, 91, 96, 106 och 107 §, 110 § 2 mom. och 111 § i folkpensionslagen samt lagen om folkpensionsindex (456/2001)."
      },
      "valid_from": "2007-05-11",
      "valid_to": null
    }
  ]
}