{
  "id": "595/2024",
  "type": "statute",
  "title": "Laki valtion virkamatkoilla sattuneiden vahinkojen korvaamisesta annetun lain 20 § :n 2 momentin kumoamisesta",
  "title_en": "Lag om upphävande av 20 § 2 mom. i lagen om skadeersättningar vid statliga tjänsteresor",
  "status": "in_force",
  "issued_date": "2024-11-08",
  "in_force_date": "2024-11-08",
  "url": "https://opendata.finlex.fi/finlex/avoindata/v1/akn/fi/act/statute/2024/595/fin@",
  "description": "Ingested from Finlex open data (repealing-statute)",
  "provisions": [
    {
      "provision_ref": "1",
      "section": "1",
      "content": "Tällä lailla kumotaan valtion virkamatkoilla sattuneiden vahinkojen korvaamisesta annetun lain (530/2017) 20 §:n 2 momentti.",
      "metadata": {
        "source": "finlex",
        "source_eid": "sec_1",
        "normalized_fi": "Tällä lailla kumotaan valtion virkamatkoilla sattuneiden vahinkojen korvaamisesta annetun lain (530/2017) 20 § :n 2 momentti.",
        "folded_fi": "talla lailla kumotaan valtion virkamatkoilla sattuneiden vahinkojen korvaamisesta annetun lain (530/2017) 20 §:n 2 momentti.",
        "content_sv": "Genom denna lag upphävs i lagen om skadeersättningar vid statliga tjänsteresor (530/2017) 20 § 2 mom.",
        "normalized_sv": "Genom denna lag upphävs i lagen om skadeersättningar vid statliga tjänsteresor (530/2017) 20 § 2 mom.",
        "folded_sv": "genom denna lag upphavs i lagen om skadeersattningar vid statliga tjansteresor (530/2017) 20 § 2 mom."
      }
    },
    {
      "provision_ref": "2",
      "section": "2",
      "content": "Tämä laki tulee voimaan 13 päivänä marraskuuta 2024.",
      "metadata": {
        "source": "finlex",
        "source_eid": "sec_2",
        "normalized_fi": "Tämä laki tulee voimaan 13 päivänä marraskuuta 2024.",
        "folded_fi": "tama laki tulee voimaan 13 paivana marraskuuta 2024.",
        "content_sv": "Denna lag träder i kraft den 13 november 2024.",
        "normalized_sv": "Denna lag träder i kraft den 13 november 2024.",
        "folded_sv": "denna lag trader i kraft den 13 november 2024."
      }
    }
  ],
  "provision_versions": [
    {
      "provision_ref": "1",
      "section": "1",
      "content": "Tällä lailla kumotaan valtion virkamatkoilla sattuneiden vahinkojen korvaamisesta annetun lain (530/2017) 20 §:n 2 momentti.",
      "metadata": {
        "source": "finlex",
        "source_eid": "sec_1",
        "normalized_fi": "Tällä lailla kumotaan valtion virkamatkoilla sattuneiden vahinkojen korvaamisesta annetun lain (530/2017) 20 § :n 2 momentti.",
        "folded_fi": "talla lailla kumotaan valtion virkamatkoilla sattuneiden vahinkojen korvaamisesta annetun lain (530/2017) 20 §:n 2 momentti.",
        "content_sv": "Genom denna lag upphävs i lagen om skadeersättningar vid statliga tjänsteresor (530/2017) 20 § 2 mom.",
        "normalized_sv": "Genom denna lag upphävs i lagen om skadeersättningar vid statliga tjänsteresor (530/2017) 20 § 2 mom.",
        "folded_sv": "genom denna lag upphavs i lagen om skadeersattningar vid statliga tjansteresor (530/2017) 20 § 2 mom."
      },
      "valid_from": "2024-11-08",
      "valid_to": null
    },
    {
      "provision_ref": "2",
      "section": "2",
      "content": "Tämä laki tulee voimaan 13 päivänä marraskuuta 2024.",
      "metadata": {
        "source": "finlex",
        "source_eid": "sec_2",
        "normalized_fi": "Tämä laki tulee voimaan 13 päivänä marraskuuta 2024.",
        "folded_fi": "tama laki tulee voimaan 13 paivana marraskuuta 2024.",
        "content_sv": "Denna lag träder i kraft den 13 november 2024.",
        "normalized_sv": "Denna lag träder i kraft den 13 november 2024.",
        "folded_sv": "denna lag trader i kraft den 13 november 2024."
      },
      "valid_from": "2024-11-08",
      "valid_to": null
    }
  ]
}